{
  "modules": [
    {
      "events": 100,
      "label": "source",
      "mem_alloc": 324010,
      "mem_free": 117879,
      "time_real": 638.442992,
      "time_thread": 636.611428,
      "type": "PoolSource"
    },
    {
      "events": 100,
      "label": "TriggerResults",
      "mem_alloc": 20,
      "mem_free": 3,
      "time_real": 0.252878,
      "time_thread": 0.25023,
      "type": "TriggerResultInserter"
    },
    {
      "events": 100,
      "label": "raw2digi_step",
      "mem_alloc": 7,
      "mem_free": 3,
      "time_real": 0.453027,
      "time_thread": 0.484236,
      "type": "PathStatusInserter"
    },
    {
      "events": 100,
      "label": "reconstruction_step",
      "mem_alloc": 7,
      "mem_free": 3,
      "time_real": 0.22922,
      "time_thread": 0.223978,
      "type": "PathStatusInserter"
    },
    {
      "events": 100,
      "label": "pixel_tracks_step",
      "mem_alloc": 7,
      "mem_free": 3,
      "time_real": 0.171475,
      "time_thread": 0.186788,
      "type": "PathStatusInserter"
    },
    {
      "events": 100,
      "label": "pre_validation_step",
      "mem_alloc": 7,
      "mem_free": 3,
      "time_real": 0.218353,
      "time_thread": 0.217729,
      "type": "PathStatusInserter"
    },
    {
      "events": 100,
      "label": "validation_step",
      "mem_alloc": 7,
      "mem_free": 3,
      "time_real": 0.402939,
      "time_thread": 0.421384,
      "type": "PathStatusInserter"
    },
    {
      "events": 100,
      "label": "consume_step",
      "mem_alloc": 7,
      "mem_free": 3,
      "time_real": 0.294066,
      "time_thread": 0.294895,
      "type": "EndPathStatusInserter"
    },
    {
      "events": 0,
      "label": "",
      "mem_alloc": 0,
      "mem_free": 0,
      "time_real": 0.0,
      "time_thread": 0.0,
      "type": ""
    },
    {
      "events": 100,
      "label": "siPixelRecHitsPreSplitting@cuda",
      "mem_alloc": 12495,
      "mem_free": 53,
      "time_real": 158.008242,
      "time_thread": 28.846968,
      "type": "SiPixelRecHitFromCUDAPhase1"
    },
    {
      "events": 0,
      "label": "",
      "mem_alloc": 0,
      "mem_free": 0,
      "time_real": 0.0,
      "time_thread": 0.0,
      "type": ""
    },
    {
      "events": 0,
      "label": "",
      "mem_alloc": 0,
      "mem_free": 0,
      "time_real": 0.0,
      "time_thread": 0.0,
      "type": ""
    },
    {
      "events": 0,
      "label": "",
      "mem_alloc": 0,
      "mem_free": 0,
      "time_real": 0.0,
      "time_thread": 0.0,
      "type": ""
    },
    {
      "events": 0,
      "label": "",
      "mem_alloc": 0,
      "mem_free": 0,
      "time_real": 0.0,
      "time_thread": 0.0,
      "type": ""
    },
    {
      "events": 100,
      "label": "tpClusterProducer",
      "mem_alloc": 764707,
      "mem_free": 761547,
      "time_real": 130.06143,
      "time_thread": 129.628246,
      "type": "ClusterTPAssociationProducer"
    },
    {
      "events": 100,
      "label": "quickTrackAssociatorByHits",
      "mem_alloc": 20,
      "mem_free": 5,
      "time_real": 0.419562,
      "time_thread": 0.421885,
      "type": "QuickTrackAssociatorByHitsProducer"
    },
    {
      "events": 100,
      "label": "simpleValidation0",
      "mem_alloc": 42500,
      "mem_free": 29314,
      "time_real": 917.261666,
      "time_thread": 119.283704,
      "type": "SimpleValidation"
    },
    {
      "events": 100,
      "label": "simpleValidation1",
      "mem_alloc": 22374,
      "mem_free": 16872,
      "time_real": 917.194274,
      "time_thread": 69.752075,
      "type": "SimpleValidation"
    },
    {
      "events": 100,
      "label": "simpleValidation2",
      "mem_alloc": 41617,
      "mem_free": 31668,
      "time_real": 925.761497,
      "time_thread": 126.414863,
      "type": "SimpleValidation"
    },
    {
      "events": 100,
      "label": "simpleValidation3",
      "mem_alloc": 29917,
      "mem_free": 22471,
      "time_real": 930.185622,
      "time_thread": 85.703552,
      "type": "SimpleValidation"
    },
    {
      "events": 100,
      "label": "simpleValidation4",
      "mem_alloc": 54092,
      "mem_free": 30997,
      "time_real": 962.647486,
      "time_thread": 128.949248,
      "type": "SimpleValidation"
    },
    {
      "events": 100,
      "label": "consumer",
      "mem_alloc": 0,
      "mem_free": 0,
      "time_real": 0.151028,
      "time_thread": 0.188336,
      "type": "GenericConsumer"
    },
    {
      "events": 100,
      "label": "offlineBeamSpot",
      "mem_alloc": 257,
      "mem_free": 194,
      "time_real": 1.478421,
      "time_thread": 1.475143,
      "type": "BeamSpotProducer"
    },
    {
      "events": 100,
      "label": "offlineBeamSpotToCUDA",
      "mem_alloc": 91,
      "mem_free": 13,
      "time_real": 5.181972,
      "time_thread": 3.89011,
      "type": "BeamSpotToCUDA"
    },
    {
      "events": 100,
      "label": "pixelTracks0",
      "mem_alloc": 16056,
      "mem_free": 5425,
      "time_real": 17.031994,
      "time_thread": 16.969238,
      "type": "PixelTrackProducerFromSoAPhase1"
    },
    {
      "events": 100,
      "label": "pixelTracks1",
      "mem_alloc": 16641,
      "mem_free": 5612,
      "time_real": 17.092835,
      "time_thread": 16.987913,
      "type": "PixelTrackProducerFromSoAPhase1"
    },
    {
      "events": 100,
      "label": "pixelTracks2",
      "mem_alloc": 16990,
      "mem_free": 5714,
      "time_real": 18.256274,
      "time_thread": 18.130981,
      "type": "PixelTrackProducerFromSoAPhase1"
    },
    {
      "events": 100,
      "label": "pixelTracks3",
      "mem_alloc": 17452,
      "mem_free": 5882,
      "time_real": 19.655603,
      "time_thread": 19.580618,
      "type": "PixelTrackProducerFromSoAPhase1"
    },
    {
      "events": 100,
      "label": "pixelTracks4",
      "mem_alloc": 17681,
      "mem_free": 5972,
      "time_real": 20.844454,
      "time_thread": 20.40492,
      "type": "PixelTrackProducerFromSoAPhase1"
    },
    {
      "events": 100,
      "label": "pixelTracksCUDA0",
      "mem_alloc": 308,
      "mem_free": 215,
      "time_real": 110.255235,
      "time_thread": 18.785244,
      "type": "CAHitNtupletCUDAPhase1"
    },
    {
      "events": 100,
      "label": "pixelTracksCUDA1",
      "mem_alloc": 461,
      "mem_free": 218,
      "time_real": 175.272446,
      "time_thread": 21.479005,
      "type": "CAHitNtupletCUDAPhase1"
    },
    {
      "events": 100,
      "label": "pixelTracksCUDA2",
      "mem_alloc": 322,
      "mem_free": 216,
      "time_real": 195.230474,
      "time_thread": 21.435074,
      "type": "CAHitNtupletCUDAPhase1"
    },
    {
      "events": 100,
      "label": "pixelTracksCUDA3",
      "mem_alloc": 304,
      "mem_free": 216,
      "time_real": 161.12143,
      "time_thread": 19.666785,
      "type": "CAHitNtupletCUDAPhase1"
    },
    {
      "events": 100,
      "label": "pixelTracksCUDA4",
      "mem_alloc": 486,
      "mem_free": 219,
      "time_real": 210.906521,
      "time_thread": 27.645464,
      "type": "CAHitNtupletCUDAPhase1"
    },
    {
      "events": 100,
      "label": "pixelTracksSoA0",
      "mem_alloc": 147,
      "mem_free": 40972,
      "time_real": 32.267322,
      "time_thread": 26.792061,
      "type": "PixelTrackSoAFromCUDAPhase1"
    },
    {
      "events": 100,
      "label": "pixelTracksSoA1",
      "mem_alloc": 150,
      "mem_free": 40972,
      "time_real": 36.085842,
      "time_thread": 30.625047,
      "type": "PixelTrackSoAFromCUDAPhase1"
    },
    {
      "events": 100,
      "label": "pixelTracksSoA2",
      "mem_alloc": 162,
      "mem_free": 40973,
      "time_real": 52.489016,
      "time_thread": 38.541832,
      "type": "PixelTrackSoAFromCUDAPhase1"
    },
    {
      "events": 100,
      "label": "pixelTracksSoA3",
      "mem_alloc": 165,
      "mem_free": 40973,
      "time_real": 67.311885,
      "time_thread": 38.645925,
      "type": "PixelTrackSoAFromCUDAPhase1"
    },
    {
      "events": 100,
      "label": "pixelTracksSoA4",
      "mem_alloc": 162,
      "mem_free": 40972,
      "time_real": 65.794423,
      "time_thread": 38.934488,
      "type": "PixelTrackSoAFromCUDAPhase1"
    },
    {
      "events": 0,
      "label": "",
      "mem_alloc": 0,
      "mem_free": 0,
      "time_real": 0.0,
      "time_thread": 0.0,
      "type": ""
    },
    {
      "events": 0,
      "label": "",
      "mem_alloc": 0,
      "mem_free": 0,
      "time_real": 0.0,
      "time_thread": 0.0,
      "type": ""
    },
    {
      "events": 0,
      "label": "",
      "mem_alloc": 0,
      "mem_free": 0,
      "time_real": 0.0,
      "time_thread": 0.0,
      "type": ""
    },
    {
      "events": 0,
      "label": "",
      "mem_alloc": 0,
      "mem_free": 0,
      "time_real": 0.0,
      "time_thread": 0.0,
      "type": ""
    },
    {
      "events": 0,
      "label": "",
      "mem_alloc": 0,
      "mem_free": 0,
      "time_real": 0.0,
      "time_thread": 0.0,
      "type": ""
    },
    {
      "events": 0,
      "label": "siPixelClustersPreSplitting",
      "mem_alloc": 0,
      "mem_free": 0,
      "time_real": 0.0,
      "time_thread": 0.0,
      "type": "SwitchProducer"
    },
    {
      "events": 100,
      "label": "siPixelClustersPreSplittingCUDA",
      "mem_alloc": 16380,
      "mem_free": 7810,
      "time_real": 64.080282,
      "time_thread": 43.832912,
      "type": "SiPixelRawToClusterCUDA"
    },
    {
      "events": 0,
      "label": "",
      "mem_alloc": 0,
      "mem_free": 0,
      "time_real": 0.0,
      "time_thread": 0.0,
      "type": ""
    },
    {
      "events": 0,
      "label": "",
      "mem_alloc": 0,
      "mem_free": 0,
      "time_real": 0.0,
      "time_thread": 0.0,
      "type": ""
    },
    {
      "events": 0,
      "label": "",
      "mem_alloc": 0,
      "mem_free": 0,
      "time_real": 0.0,
      "time_thread": 0.0,
      "type": ""
    },
    {
      "events": 100,
      "label": "siPixelDigisClustersPreSplitting",
      "mem_alloc": 49777,
      "mem_free": 25665,
      "time_real": 108.732464,
      "time_thread": 107.902558,
      "type": "SiPixelDigisClustersFromSoAPhase1"
    },
    {
      "events": 100,
      "label": "siPixelDigisSoA",
      "mem_alloc": 6853,
      "mem_free": 25,
      "time_real": 10.530452,
      "time_thread": 6.711719,
      "type": "SiPixelDigisSoAFromCUDA"
    },
    {
      "events": 0,
      "label": "siPixelRecHitsPreSplitting",
      "mem_alloc": 0,
      "mem_free": 0,
      "time_real": 0.0,
      "time_thread": 0.0,
      "type": "SwitchProducer"
    },
    {
      "events": 0,
      "label": "",
      "mem_alloc": 0,
      "mem_free": 0,
      "time_real": 0.0,
      "time_thread": 0.0,
      "type": ""
    },
    {
      "events": 100,
      "label": "siPixelRecHitsPreSplittingCUDA",
      "mem_alloc": 102,
      "mem_free": 24,
      "time_real": 12.99262,
      "time_thread": 8.210864,
      "type": "SiPixelRecHitCUDAPhase1"
    },
    {
      "events": 0,
      "label": "",
      "mem_alloc": 0,
      "mem_free": 0,
      "time_real": 0.0,
      "time_thread": 0.0,
      "type": ""
    },
    {
      "events": 100,
      "label": "other",
      "mem_alloc": 3434,
      "mem_free": 320484,
      "time_real": 13439.32005,
      "time_thread": 400.722937,
      "type": "other"
    },
    {
      "events": 100,
      "label": "eventsetup",
      "mem_alloc": 741881,
      "mem_free": 572876,
      "time_real": 1862.068325,
      "time_thread": 1804.245474,
      "type": "eventsetup"
    }
  ],
  "resources": [
    {
      "time_real": "real time"
    },
    {
      "time_thread": "cpu time"
    },
    {
      "mem_alloc": "allocated memory"
    },
    {
      "mem_free": "deallocated memory"
    }
  ],
  "total": {
    "events": 100,
    "label": "RECO",
    "mem_alloc": 2198078,
    "mem_free": 2172485,
    "time_real": 22286.156097,
    "time_thread": 4079.495857,
    "type": "Job"
  }
}